[
	{
		"word": "אטפא",
		"description": " אַטְּפָא v. [Jastrow, *אַטִּיפָא,1] "
	},
	{
		"word": "*אטקטיא",
		"description": " *אטקטיא , prob. אֲטַקְטִין ou אֲטַקְטֵי m. pl. (ἄτακτοι) troupes indisciplinées, irrégulières. Pesik. Ekhah p. 122ᵇ (expliquant : 'tes princes sont des rebelles' [Isaïe,1,23]) אדוניך מריונים דהוו מזיינין א׳ 'tes seigneurs sont des rebelles'-car ils ont équipé des irréguliers. [Cela semble être la version propre rétablie d'Ar. a. Var. ; v. Pesik. l. c. note 75]. "
	},
	{
		"word": "אטר",
		"description": " אִטֵּר, אִיטֵּר m. (b. h. [Jastrow, אִטֵּר,1], v. Hebr. Dict.), sub. יד ימינו celui dont la main droite est attachée ou inapte au travail ; gaucher. [Shabbat,103a] אי׳ יד. [Menachot,37a,5] seulement [Jastrow, א׳,1]. [Tosefta Bekhorot,5,8] א׳ בין בידיו וכ׳ ; [Bekhorot,45b,4] א׳ בין ביד וכ׳ un gaucher ou une gauchère (v. Rashi a. l.). "
	},
	{
		"word": "אטרבוליס",
		"description": " אַטְרִבֹּולִיס pr. n. pl. Tripolis, sur la côte de la Phœnicie. Y. Sabb. III, 6ᶜ top ; (Bab. [Shabbat,45b] Sidon). "
	},
	{
		"word": "אטרוגא",
		"description": " אֶטְרוֹגָא, אִיטְרוֹגָא m. (v. [Jastrow, אַתְרוֹגָא,1]) orange (arbre, a. fruit). [Targum araméen du Cantique des Cantiques,2,3] (texte h. תפוח, certaines éditions [Jastrow, אִיתְכָּלָא,1]). Y. Ab. Zar. II, 41ᵃ bot. "
	},
	{
		"word": "אטרון",
		"description": " אִטְרוֹן v. [Jastrow, אִיטְרוֹן,1] "
	},
	{
		"word": "אטרי",
		"description": " אִטְּרִי, אִטְּרִיתָא f. (נטר ; cmp. [Jastrow, הִטְּרִית,1] a. [Jastrow, טָרִית,1]) prop. quelque chose de conservé, d'où pâte conservée, vermicelles. Y. Ḥall. Je, 57ᵈ bot. car j'ai l'intention de faire אצוותי א׳ ma pâte en vermicelles. Y. Bets. Moi, 60ᵈ הדא אטריתא וכ׳ de faire du verm. (les jours saints), si pour les sécher, il est interdit &c. "
	},
	{
		"word": "אטרכונא",
		"description": " אֲטַרְכוֹנָא pr. n. pl. Trachonitis, un district à l'est de Gaulanitis. [Targum Jérusalem, Deutéronome,3,14] (h. Argob). V. [Jastrow, טְרָכוֹנָא,1]. "
	},
	{
		"word": "אטרף",
		"description": " אַטְרַף, אֲטְרְפָא m. (= [Jastrow, טַרְפָא I,1], h. [Jastrow, טֶרֶף,1]) feuille. [Gittin,69b,20] (collect.).-Pl. אַטְרְפִין, אַטְרְפֵי. [Targum araméen des Psaumes, 1,3]. [Bava Metzia,114b] (Var. טרפי, v. Rabb. D. S. a. l.). "
	},
	{
		"word": "אי־",
		"description": " אִי- préfixe, v. [Jastrow, אִ-,1]. "
	},
	{
		"word": "אי",
		"description": " אִי I fem. de [Jastrow, אוּ,1] q. v. "
	},
	{
		"word": "אי",
		"description": " אִי II, אֵי I (= [Jastrow, אִין I,1] ; h. [Jastrow, אִם,1] ; cmp. [Jastrow, אוֹ,1]) 1) si, si. [Targum araméen du Cantique des Cantiques,7,13] ; a. e.-[Berakhot,2a,10], a. fr. אי הכי (abbrev. א \"ה) si cela est ainsi (introduire un argument contre son opinion). -[Rosh Hashanah,3a,2] כי משמש וכ׳ khi a quatre significations, אי si, &c.-אי נמי (abbrev. א \"נ) a) si tu choisis, on peut aussi le dire ; ou. [Bava Metzia,98a,8] ; a. fr.-b) même si, v. [Jastrow, נַמִּי,1]. [Chullin,12a,10] א \"נ דילמא וכ׳ (Rashi א \"נ שמע איניש וכ׳) même si quelqu'un d'autre l'a entendu ; a. fr.-אי אמרת בשלמא (abbr. אא \"ב = בשלמא אי אמרת) Je vous l'accorde, si vous disiez... [Jastrow, הַיְינוּ,1] alors serait juste ce que &c. ; v. [Jastrow, בִּשְׁלָמָא,1]. [Yoma,17b,1] ; a. fr.-אי ... אי si ... ou. [Targum araméen de l'Ecclésiaste, 11,6]. [Bava Metzia,98a,8] ; a. fr. -2) adv. d'interrogation, v. [Jastrow, אִין II,1]. [Targum araméen de Job,11,2] Ms. (éd. אין). "
	},
	{
		"word": "אי",
		"description": " אִי III (= h. [Jastrow, אֵין,1]) not. [Mishna Gittin,4,5] אי אפשר c'est impossible. [Mishnah Ketubot,12,3] אי אפשי je ne veux pas ; a. fr. "
	},
	{
		"word": "אי",
		"description": " אִי IV (abbr. de [Jastrow, אִית,1], comme [Jastrow, לֵי,1] = [Jastrow, לַיִת,1]) il y a. Y. Snh. VI, 23ᵇ bot. אי בי וכ׳ il y a en moi (la possibilité de) faire, c'est-à-dire que je peux le faire. [Yoma,2a] מה אי וכ׳ qu'est-ce que tu peux faire ? (v. Y. Ḥag. II, 78ᵃ haut). "
	},
	{
		"word": "אי",
		"description": " אֵי II (b. h. [Jastrow, אִי IV,1] [Jastrow, אִי IV,1]) Interj. Eh ! Oh ! Malheur ! [Targum Jérusalem, Lévitique,26,29].-[Taanit,7a,17] אי חכמה וכ׳ Oh, pour un esprit aussi brillant dans un vaisseau (corps) aussi laid ! [Rosh Hashanah,19a,6] אי שמים Oh cieux! ; a. fr. Y. Shek. V, fin, 49ᵇ אי לי שאני וכ׳ malheur à moi, que je te voie ainsi ! Y. Yeb. XIII, 14ᵃ top ; a. fr. [Babli, généralement [Jastrow, אוֹי,1].] "
	},
	{
		"word": "אי",
		"description": " אֵי III ([Jastrow, אֵיי,1]) h. (b. h. [Jastrow, אִי II,1], [Jastrow, אַיָּה,1]) où ? quoi ? comment?-אי מנן d'où ? [Targum Jonathan sur Josué,2,4] ; a. e.-Héb. אי זה (souvent [Jastrow, אֵיזֶה,1], [Jastrow, אֵיזֶה,1] en un seul mot) qui ? lequel ? Y. Kil. VIII, beg. 31ᵇ לאי זה דבר נאמר à l'égard de quoi (de quelle manière, sens) a-t-on dit ? Y. Shebi . Je, supplie. 33ᵃ ואי זה זה et de quel (temps de labour) s'agit-il ? ; a. v. fr.-Y. Peah III, 17ᶜ top ואיי דינו מירוג (= אידין) et quel est le sens de merog ? Kerith. 6ᵇ לאיי מיצרך צריכי quel besoin y a-t-il (des autres) ? Cmp. [Jastrow, אֵיזֶה,1] ; [Jastrow, אֵימָתַי,1] ; <[Keritot,6b,31] לאיי מיצרך צריכי quel besoin y a-t-il (des autres) ? Cmp. [Jastrow, אֵיזֶה,1] ; [Jastrow, אֵימָתַי,1] ; [Jastrow, כֵּיצַד,1]. "
	},
	{
		"word": "איב",
		"description": " אֵיב v. [Jastrow, אֵב,1]. "
	},
	{
		"word": "איבא",
		"description": " אִיבָּא I, אִבָּא m. (cmp. [Jastrow, אֵב,1]) croissance, fruit. [Onkelos Genèse,4,3] ; a. e. ; v. [Jastrow, אִנְבָּא I,1]. "
	},
	{
		"word": "איבא",
		"description": " אִיבָּא II, אִיבָא m. = [Jastrow, אַבָּא I,1] père. [Targum Jonathan sur les Nombres, 30,4] ; a. fr. "
	},
	{
		"word": "*איבבא",
		"description": " *אִיבְבָא = [Jastrow, אִיבָּא I,1] I, pl. איבְבַיָּא. [Targum Jonathan sur I Rois, 6, 38] (éd. Vien. אִבְּבַיָא). "
	},
	{
		"word": "איבה",
		"description": " אֵיבָה f. (b. h. ; אָיַב, √ [Jastrow, אוֹ I,1] ou [Jastrow, אָב I,1], cmp. [Jastrow, אַכְאָבִית,1], [Jastrow, אָוֶן,1], [Jastrow, עָוֹן,1][Jastrow, עָוֹן,1]) 1) inimitié, hostilité, rancune. [Mishna Sanhedrin,3,5] un ennemi est celui qui n'a pas parlé à son voisin depuis trois jours בא׳ dans sa rancune ; a. fr.-משום (מפני) [Jastrow, א׳,1] dans le but de prévenir les mauvais sentiments. Y. Dem. IV, 24ᵃ ; a. fr. -2) aversion, dégoût, perte d'attrait. Y. Yoma VIII, 44ᵈ bot. הכלה מפני א׳ la mariée (est autorisée à se laver le visage le jour de l'expiation.) afin qu'elle ne perde pas son attrait. "
	},
	{
		"word": "איבו",
		"description": " אִיבּוּ, אִבּוּ, (אִיבֹּו) f. (אנב, √ [Jastrow, אָב I,1]. cmp. [Jastrow, אָבֵל I,1]) [noir], nom d'un oiseau (h. אֲנָפָה) vautour ou milan. [Onkelos Lévitique,11,19] ; [Deutéronome,14,18] (Targ. Y. אוכמתא). Targum Jonathan sur Deutéronome,14,13], [Targum Jérusalem, Deutéronome,14,13] ; [Targum Jérusalem, Deutéronome,14,14], glose au v. 18 ; confondu avec le texte du v. 13-h. [Jastrow, אַיָּה,1].]-[Jastrow, אִיבּוּ,1] pr. n. m, v. [Jastrow, אִבּוּ,1]. "
	},
	{
		"word": "איבוד",
		"description": " אִיבּוּד m. (אבד) ruine, destruction. [Avodah Zarah,33a] אזיל לא׳ est gaspillé. [Chullin,11b,6] משום א׳ נשמה pour éviter la perte de vie (pour sauver le condamné). [Beitzah,22a,11] אִבּוּד ממון perte pécuniaire ; a. fr. "
	},
	{
		"word": "איבול",
		"description": " אִיבּוּל I m. ([Jastrow, אָבֵל I,1]) deuil ; v. [Jastrow, אֲבֵילוּת,1]. [Mishnah Yevamot,4,10] ; a. e. "
	},
	{
		"word": "איבול",
		"description": " אִיבּוּל II, אִיבּוּלָא ch., v. [Jastrow, אֵיבָרָא,1]. "
	},
	{
		"word": "איבוס",
		"description": " אֵיבוּס v. [Jastrow, אֵבוּס,1] "
	},
	{
		"word": "*איבוס",
		"description": " *איבּוּס, כפר א׳ , v. אָמוּס "
	},
	{
		"word": "איבוס",
		"description": " אִיבּוּס m. ([Jastrow, אָבַס,1]) bourrer, forcer la nourriture dans la gorge de l'animal. [Eruvin,20b,17] (première fois) והא אי׳ כמאן וכ׳ dans le bourrage, n'est-ce pas comme prendre un récipient en main &c. ? [Deuxième temps והא א׳ כמאן וכ׳ omis dans Ms. M.] "
	},
	{
		"word": "*איביריתא",
		"description": " *אִיבִּירְיָתָא, אִיבִּירְיָתָה f. pl. (prob. contr. de איבעיר׳ ; [Jastrow, בְּעַר I,1]), א׳ דזהרא lampistes, servantes qui s'occupaient des lumières. Y. Yoma III, beg. 40ᵇ ; Y. R. Hash. II, beg. 57ᵈ R. ... manipulait des choses qu'il était interdit de manipuler le jour du sabbat על פום א׳ דז׳ (Y. R. Hash. l. c., encart [Jastrow, פּוּם,1]) sur la déclaration des allumeurs de lampes que la nuit était entrée (חשיכה מוצאי שבת). [Le contexte prouve que notre w. désigne une ou des personnes]. "
	},
	{
		"word": "איבלא",
		"description": " אִיבְלָא = [Jastrow, אֶבְלָא,1]. [Onkelos Genèse,50,10] ; a. e. ed. Berl., oth. ed. [Jastrow, אֶבְלָא,1]. "
	},
	{
		"word": "איבליים",
		"description": " אֵיבְלַיִים , v. [Jastrow, אֲבֵילִין,1]. "
	},
	{
		"word": "איבעית",
		"description": " אִיבָּעִית (= [Jastrow, אִיבָּעִית,1], v. [Jastrow, בעי,1]) si tu le désires ; ou. וא׳ אימא-א׳ אימא (abr. אב \"א) si tu choisis, je peux dire... ou si tu préfères (une autre solution) je peux dire... [Yoma,28b,12] ; a. fr. "
	},
	{
		"word": "איבר",
		"description": " אֵיבֶר , pl. אֵיבָרִים, אֵיבָרִין, v. [Jastrow, אֵבֶר,1]. "
	},
	{
		"word": "איברא",
		"description": " אֵיבָרָא, אֵבְ׳ ch. (= [Jastrow, אֵיבֶר,1]) 1) membre. [Targum araméen de Job, 2,4] (Ms. [Jastrow, אִיבְרָא,1]). [Yoma,25b,14].-Trnsf. bras, aile, pignon. [Shabbat,90b] א׳ דשמאלא bras gauche.-Pl. אֵיבָרִין, אֵיבָרַיָּא. [Onkelos Leviticus,1,8], a. e. (pièces). [Targum Jonathan sur Ezéchiel,17,3] ; [Deutéronome,32,11] (ailes). -2) membrum genitale. [Targum Jonathan sur la Genèse,14,2] ; [Targum Jonathan sur la Genèse,1,27] [Targum Jonathan sur la Genèse,49,24].-Bava Metzia,84a,6], v. [Jastrow, *אִיבְרָיָה,1]]. "
	},
	{
		"word": "איברא",
		"description": " אִיבְרָא (אבר to be strong) en effet, être sûr. [Chullin,59b,9] א׳ חזינא ליה en effet, je voudrais le voir. [Gittin,56b,1] top א׳ מלכא את en effet, tu es un souverain. "
	},
	{
		"word": "*איבריאתא",
		"description": " *אִיבְרָיָאתָא f. pl. (v. [Jastrow, *אִיבְרָיָה,1]) assez pour un repas dans le ménage. [Eruvin,82b,16] תרתי רִיפָתָא א׳ Mme M. (éd. [Jastrow, אִיכַּרְיָיתָא,1], Asheri, éd. Ven. כברייתא, v. Rabb. D. S. a. l. note) deux gros pains de ménage (ou de repas de deuil). [Rashi, qui interprète notre w. comme étant les pains des conducteurs de bœufs, semble avoir eu sous les yeux les versets de Mme M. et dériver notre w. de [Jastrow, בָּרָא I,1], v. [Jastrow, בַּר,1] I a. [Jastrow, אֲפַר,1]. "
	},
	{
		"word": "*איבריה",
		"description": " *אִיבְרָיָה f. ([Jastrow, ברי,1], v. [Jastrow, הוֹבְרָיָא,1]) un repas. [Bava Metzia,84a,6] א׳ דר׳ וכ׳ un repas de R. Ismael &c. (v. Rabb. D. S. à [Jastrow, *אִיבְרָיָאתָא,1], [Eruvin,82b], note 1) ; cmp. Pesik. B'shall. p. 90ᵇ sq., a. [Berakhot,44a]). [Certains lisent [Jastrow, *אִיבְרָיָה,1] v. [Jastrow, אֵיבָרָא,1] 2)]. "
	},
	{
		"word": "איבריו",
		"description": " איבריו Y. M. Kat. III, 82ᵇ bot. lire אִיכָּרָיו ; v. [Jastrow, אִיכָּר,1]. [V. cependant, [Jastrow, *אִיבְרָיָאתָא,1] fin.] "
	},
	{
		"word": "איברייא",
		"description": " איברייא Y. M. Kat. III, fin, 83ᵈ, v. [Jastrow, הוֹבְרָיָא,1] "
	},
	{
		"word": "איגד",
		"description": " אֵיגֶד , v. [Jastrow, אֵגֶד,1] "
	},
	{
		"word": "איגור",
		"description": " אֵיגוֹר, אֵיגוֹרָא v. [Jastrow, אֵגוֹר,1] a. [Jastrow, אֱגוֹרָא I,1] [Jastrow, אֱגוֹרָא I,1]. "
	},
	{
		"word": "איגורא",
		"description": " אִיגּוּרָא = [Jastrow, אִיגָרָא,1]. [Targum Jonathan sur Sophonie,1,5] (pl.) [Jastrow, אִיגּוּרָא,1] (ed. Vien. אֱגוֹ׳). "
	},
	{
		"word": "איגורי",
		"description": " אֵיגוֹרִי v. [Jastrow, אֵגוֹרִי,1] "
	},
	{
		"word": "איגיאה",
		"description": " אִיגִיאָה f. (αἰγεία, sub. δορά) peau de chèvre. [Bereishit Rabbah,20,12], fin. "
	},
	{
		"word": "איגלא",
		"description": " איגְלָא v. [Jastrow, אִגְלָא,1]. "
	},
	{
		"word": "איגר",
		"description": " אִיגָר (אגר II) toit [voûté]. [Arakhin,32a,43] ; [Megillah,5b,15] שור א׳ une ligne urbaine formée par la jonction des toits, opp. [Jastrow, חוֹמָה,1].- "
	},
	{
		"word": "איגרא",
		"description": " אִיגָרָא, אִיגְרָא, אִגָרָא (également אִיגּ׳ avec Dagesh) const. [Jastrow, אִיגָר,1] même. [Targum araméen des Proverbes, 21,9] ; a. fr.-Ruth. R. à I, 17 (Par. 3) איגר פלטין toit du palais. [Gittin,85b] (Rashi איגרת, acc. corr.), v. [Jastrow, אִגֶּרֶת,1].-Pl. אִיגָרַיָּא, אִיגָרַיָּיא ; [Jastrow, גְּרִי,1]. [Targum Jonathan sur II Rois, 19,26] ; a. e.-Y. Pes. VII, 35ᵇ ([Shir HaShirim Rabbah,2,14] [Jastrow, *אַבְרְיָיאָה,1], acc. corr.) ; v. [Jastrow, זֵיתָא I,1]. Lam. R. introd. (R. Yoḥ. 1) ולא׳ סלקין et ils montent sur les toits. [Pesachim,111b,4] דבי א׳ ces (démons) qui habitent sur les toits. "
	},
	{
		"word": "איגרא",
		"description": " אִיגְּרָא lettre, v. [Jastrow, אִיגַּרְתָּא,1]. "
	},
	{
		"word": "איגראנאמון",
		"description": " איגראנאאמון = [Jastrow, אַגְרוֹנִימוֹס,1] q. v. "
	},
	{
		"word": "איגרת",
		"description": " אִיגֶּרֶת , v. [Jastrow, אִגֶּרֶת,1] "
	},
	{
		"word": "איגרתא",
		"description": " אִיגַּרְתָּא, אִגַּ׳ f. [Jastrow, אִיגְּרָא,1] m. (= h. [Jastrow, אִגֶּרֶת,1]) lettre &c. [Targum Jonathan sur II Rois,5,5] ; a. fr.-Y. Ned. X, fin, 42ᵇ, a. e. א׳ דאיקר lettre d'honneur, de recommandation. [Shabbat,115a,1] ; a. fr.-[Bava Metzia,83b] ; [Sanhedrin,82a] ; [Sanhedrin,96a,12] (prov.) קריינא דא׳ איהו ליהוי פרוונקא que celui qui a composé la lettre soit lui-même son porteur.-Pl. (de [Jastrow, אִיגְּרָא,1]) אִיגְּרִין. [Targum Jérusalem, Nombres, 22,7] [Jastrow, אִיגַּרְתָּא,1].- [Targum Jonathan sur Isaïe, 39,1].-אִיגָּרָן, אִיגָּרָאן, [Jastrow, אִיגַּרְתָּא,1], אִיגָּרָאתָא. [Targum Jonathan sur I Rois, 21,9] ; a. fr.-Y. Keth. II, 26ᵇ bot. Y. Ned. VI, 40ᵃ bot. Y. Snh. I, 19ᵃ bot. "
	},
	{
		"word": "איד",
		"description": " אֵיד m. (b. h. ; [Jastrow, אוּד,1], [Jastrow, עוּד,1], cmp. [Jastrow, עֵת,1], [Jastrow, אִידָּנָא,1][Jastrow, אִידָּנָא,1]) tourner, échéance, d'où 1) mauvais sort, renversements. [Bereishit Rabbah, 13,12], v. [Jastrow, אֵד,1]. -2) anniversaire, fête idolâtre. [Avodah Zarah,7b,6] יום אֵידָם le jour même de leur fête.-Pl. אֵידִים. [Mishnah Avodah Zarah,1,2], a. fr. (של נכרים) אֵידֵיהֶן. [Avodah Zarah,2a,3] ; Y. Erub. V, beg. 22ᵃ (controverse sur l'orthographe avec [Jastrow, א׳,1] ou avec [Jastrow, ע,1]). [Quant à la désignation cacophémique, cmp. [Jastrow, אֲבֵידָן,1] &c.] "
	},
	{
		"word": "אידא",
		"description": " אֵידָא I, עֵידָא, עֵדָא ch. [Jastrow, אֵיד,1]. [Targum araméen d'Esther, 1,3]. [Targum araméen des Proverbes,7,20]. "
	},
	{
		"word": "אידא",
		"description": " אֵידָא II , v. [Jastrow, אֵידֵין,1] a. [Jastrow, הֵידָא,1][Jastrow, הֵידָא,1]. "
	},
	{
		"word": "אידא",
		"description": " אִידָא I, אַיְדָא f. (= [Jastrow, יַד,1] ; v. [Jastrow, אִ-,1]) main (seulement dans le Targ. Y.). [Targum Jonathan sur Deutéronome,9,26] ; a. fr.-Pl. אִידַיָּא, אַיְדַיָּא, [Jastrow, אִידֵּי,1]. [Targum araméen des Psaumes, 24,4] ; a. fr. "
	},
	{
		"word": "אידא",
		"description": " אִידָא II f. (= אִי דָא, v. [Jastrow, אוּ,1] a. [Jastrow, דָּא I,1][Jastrow, דָּא I,1])ce, le même. Y. Erub. III, 21ᵇ bot. הדא אמרה אי א׳ אי א׳ ceci prouve que ceci est ceci, ceci est cela, c'est-à-dire que c'est le même. Yoma,2a] היא הדא היא הדא.] "
	},
	{
		"word": "אידא",
		"description": " אִידָּא laine, v. [Jastrow, אוּדְדָא,1], a. [Jastrow, אִירָא,1]. "
	},
	{
		"word": "אידור",
		"description": " אִידוֹר m. (ὕδωρ) eau. [Sukkah,35a,5] ; v. [Jastrow, הִידוֹר,1]. "
	},
	{
		"word": "אידותא",
		"description": " אִידוּתָא v. [Jastrow, אַדְווּתָא,1] "
	},
	{
		"word": "אידי",
		"description": " אִידֵּי pl. de [Jastrow, אִידֵּךְ,1]. "
	},
	{
		"word": "אידי",
		"description": " אִידִי, אִידִית pr. n. m. Idi, Idith, un Amora. Y. Yoma VII, beg. 44ᵃ. [Sanhedrin,38b,8] ; a. e. "
	},
	{
		"word": "אידין",
		"description": " אֵידֵין, אֵידְנָא, אַיְידָא אֵידָא, (אַיְידִי) f. (h. [Jastrow, אֵיזֶה,1], [Jastrow, אֵיזוּ,1] [Jastrow, אֵיזוּ,1]) 1) qui maintenant ? quoi maintenant ? lequel maintenant ? (quisnam, quidnam). [Targum Jonathan sur I Samuel, 6,20]. [Targum Jonathan sur Jérémie,2,10] ; a. fr.-[Tamid,32a,29] א׳ מתקרי חכים qui sera appelé sage ? [Eichah Rabbah,1,1] (חד מאת׳ 4) אחמי לי אידא וכ׳ montre-moi maintenant lequel de ceux-ci provient d'un bouc blanc &c. Y. Pes. II, 28ᶜ top ואיידא אמר דא quel (passage) dit maintenant ceci (est-ce dérivé de) ? Y. Sot. V, 20ᶜ bot. ואיידי חובתא עבדית et quel est le péché que j'ai commis ? [Eichah Rabbah,3] באידנא אסטרטיא וכ׳ par quelle route es-tu venu ?  2) (ellipt.) que voulez-vous ? Y. B. Kam. V, supplie. 4ᵈ, v. [Jastrow, הֵידָא,1]. "
	},
	{
		"word": "אידיני",
		"description": " אִידְיָנִי , v. אוּדְ׳ "
	},
	{
		"word": "אידית",
		"description": " אִידִית , v. [Jastrow, אִידִי,1]. "
	},
	{
		"word": "אידך",
		"description": " אִידֵּךְ m. a. fem. (= [Jastrow, דֵּךְ,1], avec [Jastrow, אִי IV,1] prosth.) ceci, cela, freq. l'autre, un autre. [Yevamot,62a,8] ; a. fr. תניא א׳ un autre (auteur ou Boraitha) enseigne. [Yevamot,22b,17] בא׳ קרא dans un autre verset. [Bava Metzia,98b,1] וא׳ לא ידענא et quant à l'autre (vache), je ne sais pas ; a. fr.-Pl. [Jastrow, אִידֵּי,1].-א׳ וא׳ ceux-ci et ceux-là, c'est-à-dire les deux. [Yevamot,8a,15] ; a. fr. "
	},
	{
		"word": "אידכרו",
		"description": " אִידְכָּרוּ v. [Jastrow, אִדְכָּרוּ,1]. "
	},
	{
		"word": "*אידן",
		"description": " *אִידָּן m. (אדד, v. [Jastrow, אוּדְרָא,1]) bas-coton, &c., en particulier bâtard tordu pour une mèche. [Mishna Shabbat, 2,1], expl. dans Babli (20ᵇ) אחוינא, v. [Jastrow, אַחְוָונָא,1] 3), dans Y. (4ᶜ) עידניתא. "
	},
	{
		"word": "אידנא",
		"description": " אֵידְנָא v. [Jastrow, אֵידֵין,1] "
	},
	{
		"word": "אידנא",
		"description": " אִידָּנָא, אִידְּנָא m. (= [Jastrow, עִידָּן,1], [Jastrow, עִידָּן ²,1] ; [Jastrow, אוּד,1], עוד) time.-הָאִידְּנָא this time, now, to-day. [Targum Jonathan sur Deutéronome,1,6] (usu. avec [Jastrow, ע,1]).-[Yevamot,62a,5] לילא דהא׳ cette nuit. [Yoma,19b,16] הא׳ יומא וכ׳ aujourd'hui est le jour de l'expiation. [Berakhot,4a,7] כי הא׳ à ce moment précis (heure). [Kiddushin,71b,2] והא׳ דאיכא רמאי mais de nos jours où il y a des trompeurs ; a. fr. "
	},
	{
		"word": "אידר",
		"description": " אִידַּר, אִידְּרָא v. [Jastrow, אִדַּר,1]. "
	},
	{
		"word": "*אידרוטירון",
		"description": " *אידרוטירון , lu "
	},
	{
		"word": "*אידרומילון",
		"description": " *אִידְרוֹמִילוֹן m. (ὑδρόμηλον) un cidre de gelée de coing. Y. Shebi. III, beg. 37ᵇ "
	},
	{
		"word": "אידרון",
		"description": " אִידְּרוֹן, אִידְּרוֹנָא, אִינְדְּרוֹנָא, אִנְדְּרוֹנָא m. ([Jastrow, אֵדֶר I,1] ; Assyr. idrânu, v. Fred. Del. Hebr. Lang. p. 24 ; cmp. [Jastrow, חֶדֶר,1]) une enceinte, une chambre, en particulier une alcôve sombre, une chambre à coucher. [Targum araméen de Job,37,9]. [Megillah,26b,13] איד׳ דהוה וכ׳ une pièce où le cadavre était placé avant l'enterrement. [Bava Batra,7a,11] השתא משוית לי איד׳ ed. (Ms. M. והשתא אינד׳) maintenant tu fais de mon compartiment (autrefois ouvert) une alcôve sans lumière. [Chullin,52b,16] ; par exemple - [Menachot,33b] (fem.) א׳ מעלייתא une belle pièce. [Bava Kamma, 85b], v. [Jastrow, הַרְזֵק,1]. [Taanit,25a,1] עיילא לאינ׳ elle est montée dans la chambre à coucher. "
	},
	{
		"word": "אידרונה",
		"description": " אִידְּרוֹנָה = [Jastrow, אִידְּרוֹן,1] "
	},
	{
		"word": "אידרי",
		"description": " אִידְּרִי v. [Jastrow, דְּרֵי II,1] "
	},
	{
		"word": "אידרעא=אדרעא",
		"description": " אִידְרְעָא = אֶדְרְעָא "
	},
	{
		"word": "*אידרתו",
		"description": " *אידרתו , [Kohelet Rabbah,4,7,1] זו אידרתו של מלאך המות (Var. in Y'dê Mosheh a. l. של א \"ה), une corruption d'une clause mutilée, dont une partie se trouve dans [Devarim Rabbah,2] où [Proverbes, 24,21] est réprouvé et Salomon est amené à l'amender par [Ecclésiaste,4,8] יש אחד ואין שני. Le passage rétabli serait probablement le suivant : זו ירא את ר׳ בני ומלך עם וג׳. אמר ר׳ אחא כעס הקב \"ה ... חזר ופירש את הדבר יש אחד ואין שני וכ׳. "
	},
	{
		"word": "*אידתיקרימא",
		"description": " *אידתיקרימא Y. Dem. V, 24ᵈ, une corruption ; prob. אִינוֹקְפֵילַיָּא m. pl. (οἰνοκάπηλοι) gardiens de boutiques de vin, opp. שפייא ; q. v. "
	},
	{
		"word": "איה",
		"description": " אַיָּה pr. n. m. Ayah. [Gittin,35a,17] א׳ מרי A. Mari, nom de famille d'un Aḥa b. Hidya. "
	},
	{
		"word": "איהא",
		"description": " אִיהָא (v. [Jastrow, אִיהוּ,1] a. [Jastrow, הָא I,1]) que, le même. [Targum araméen sur Ruth,1,16]. "
	},
	{
		"word": "איהו",
		"description": " אִיהוּ, אִיהוּא m. , [Jastrow, אִיהִי I,1] f. (= [Jastrow, הוּ,1], [Jastrow, הוּא ²,1], v. [Jastrow, אִ-,1]) il, lui-même ; elle, elle-même. [Targum Jonathan sur le Lévitique, 5,3]. [Targum araméen sur Esther,1,1] ; a. v. fr.-[Bereishit Rabbah,49,11] יסב א׳ וכ׳ se laisse prendre la cendre ; a. fr.-Pl. [Jastrow, אִינְהוּ,1] m., [Jastrow, אִינְהוּ,1] f. ; [Jastrow, נִיהוּ,1], [Jastrow, נִינְהוּ,1] ; [Jastrow, אִינָךְ,1], [Jastrow, אִינוּן,1] m., [Jastrow, אִינִין,1] f. (contr. [Jastrow, אִנּוּן,1], [Jastrow, אָנִין,1]) ; très fréquent -Y. Bicc. II, fin, 65ᵇ דינון מרין = דאינון אמרין. Y. Meg. I, 71ᵃ top אילין אינין y a-t-il seulement ces (différences entre le sabbat et les fêtes) ? "
	},
	{
		"word": "איהי",
		"description": " אִיהִי I v. [Jastrow, אִיהוּ,1] "
	},
	{
		"word": "*איהי",
		"description": " *אִיהִי II , א׳ דַקִּירָא ([Jastrow, הַאי,1]) pr. n. pl. Ihi Dakkira, Is, une ville sur les rives ouest de l'Euphrate, et sur une petite rivière du même nom ; (v. Rapap. Er. Mill. p. 33, a. Sm. Class. Dict. s. v. Is). [Kiddushin,72a] א׳ ד׳ (Ar. [Jastrow, הַאי,1]). [Bava Batra,24a] Ms. R. א׳ דקי׳ (ed. האי דקרא, v. Rabb. D. S. a. l.). [Berakhot,59b] (v. Rabb. D. a. l.). "
	},
	{
		"word": "איו",
		"description": " אַיּוֹ pr. n. m. Ayo, un érudit. [Beitzah,37b,18] ; a. fr. "
	},
	{
		"word": "איוב",
		"description": " אִיֹּוב (b. h.) pr. n. m. Job, le personnage après lequel le livre biblique (ספר א׳) le Livre de Job est nommé. [Bava Batra,14b,11] ; [Bava Batra,15a,17] sq. Y. Sot. V, fin, 20ᶜᵈ. [Niddah,52a,62] ; [Niddah,52b,3] ; a. fr. "
	},
	{
		"word": "איוונטיאות",
		"description": " איוונטיאות [Yalkut Shimoni sur la Torah,376], lire אוותנטאות, v. [Jastrow, אַוְותֶּנְטִי,1]. "
	},
	{
		"word": "איויא",
		"description": " אִיוְיָא , v. [Jastrow, אִוְיָא I,1] "
	},
	{
		"word": "איול",
		"description": " איול, אייול , v. [Jastrow, אַיִל,1] 2). "
	},
	{
		"word": "איזא",
		"description": " אִיזָּא , pl. אִיזַיָּא m. (אזז, cmp. [Jastrow, גְּזִיזָא,1], [Jastrow, חָזִיז,1], אזד) rameaux épineux. Y. Maas. Sh. IV, 55ᵇ bot. (à celui qui rêvait que les gens couraient devant lui - signifiant le pouvoir) דאת מייתי א׳ וכ׳ tu porteras des rameaux épineux et tout le monde te fuira. [V. Lam. R. quot. s. v. [Jastrow, גְּבַב,1]. "
	},
	{
		"word": "איזביון",
		"description": " אֵיזֹבְיָוָן , v. [Jastrow, אֵזוֹב,1]. "
	},
	{
		"word": "איזגד",
		"description": " אִיזְגַּד, אִיזְגַּדָּא (Targ. Y. [Jastrow, עִזְגַּד,1], [Jastrow, עִזְגַּד,1]) m. (contr. de גזגזדא, [Jastrow, ג,1] adouci en [Jastrow, א,1] ou [Jastrow, ע,1], cmp. אזד, [Jastrow, *אַדְרַזְדָּא,1] ; aussi מזדנדז = מזדעזע, s. v. זעזע ; Massorah אִיסְגַּד-, אִסְגַּד-, Ispe. de גזז ; Berl. Targ. O. II, p. 63, 68 ; cmp. Mand. אשגאנדא, Nöld. Mand. Gr. lithog. table ; v. [Jastrow, גּוּז,1], גזז) coureur. [Targum Jonathan sur la Genèse,49,21] ע׳ קליל un coureur léger ; a. e. En gen. messager.  Pl. אִיזְגַּדִּין, [Jastrow, אִיזְגַּד,1], [Jastrow, עִזְקָא ²,1], [Jastrow, עֻזְיָא,1], [Jastrow, *אִסְטַבְלָא,1]. [Targum Jonathan sur Isaïe, 18,2] ; a. v. fr. "
	},
	{
		"word": "איזגדר",
		"description": " אִיזְגְּדַר pr. n. m. (pour איזדגרד) Yesdigerd, Yezdjird, un roi perse. [Zevachim,19a,2] haut. [Ketubot,61a] bot. אזגוד (corr. acc.). "
	},
	{
		"word": "*איזגרא",
		"description": " *אִיזְגָּרָא m. , pl. אִיזְגָּרִין ([Jastrow, גָּרַר I,1], v. [Jastrow, אֵגוֹר,1] ; préfixe [Jastrow, *אִזְתַּוְודָּא,1], cmp. [Jastrow, אִיזְמֵיל,1] a. [Jastrow, אִיזְגַּד,1]) monticules. [Bereishit Rabbah,74] בחקל דאית ביה א׳ וכ׳ dans un champ dans lequel il y a des monticules (derrière lesquels on peut se cacher) parler pas de secrets. [Muss. incorr. [Jastrow, ד,1] pour [Jastrow, ר,1].] "
	},
	{
		"word": "איזדקר",
		"description": " אִיזְדקַר v. [Jastrow, זְקַר,1]. "
	},
	{
		"word": "איזה",
		"description": " אֵיזֶה, אֵיזֶהוּ, אֵזֶ׳ m. , [Jastrow, אֵיזוּ,1] f. (b. h. qui ? quoi ? lequel ? [Pirkei Avot,4,1] איזהו חכם qui est sage? ; a. v. fr.-באיזה צד de quelle manière, v. [Jastrow, כֵּיצַד,1]. [Chald. [Jastrow, אֵידֵין,1], [Jastrow, אָדָא II,1].] "
	},
	{
		"word": "איזו",
		"description": " אֵיזוּ , v. [Jastrow, אֵיזֶה,1], a. [Jastrow, אֵיזִי,1]. "
	},
	{
		"word": "איזוב",
		"description": " אֵיזוֹב, אֵיזוֹבָא , v. [Jastrow, אֵיזֶה,1]. "
	},
	{
		"word": "איזי",
		"description": " אֵיזִי, אֵיזוּ (v. [Jastrow, אֵיזֶה,1] = b. h. אֵיפוֹא, אֵפֹה, [Jastrow, אפו,1]) maintenant, alors, prie. [Yoma,30b,10] אודו לי א׳ (miss. dans Mss., Ms. M. 2 זי) admettez alors au moins. [Bava Metzia,70a,2] אימא לי איזו dis-moi maintenant ; a. e. V. [Jastrow, הֵידֵין,1]. "
	},
	{
		"word": "איזלא",
		"description": " אִיזְלָא, אוּזְלָא, אוּזַלְתָּא f. (אֲזַל II) web, net, etc. [Chullin,51b,14] אי׳ ומקרבי קיטרי un filet dans lequel les nœuds sont serrés. [Eruvin,28b,21] אוזלתא דאיכרי Mme M. (éd. [Jastrow, אוּזִילְתָּא,1], Ar. איזולתא) la torsion (des grappes) du cultivateur.-Pl. אִיזְלֵי. [Moed Katan,11a,2]. [Gittin,60b] אוּזְלֵי ; v. [Jastrow, אוֹהֲרָא,1].-[Eruvin,8a,13] פסק ליה לסורא באו׳ (ed. Sonc. [Jastrow, אִסְקְרִיטִין,1]) il sépara les cours de Sura avec des filets (haies, nattes). "
	},
	{
		"word": "איזמא",
		"description": " אִיזְמָא m., v. [Jastrow, הִיזְמָא,1]. [Tosefta Kilaim,1,11] ed. Zuck. (ed. corrompu [Jastrow, אזמאזמא,1]). "
	}
]