[
	{
		"word": "גין",
		"description": " גִּין I (v. [Jastrow, גּוּן,1]), Af. אָגֵין (avec על) couvrir, entourer de ; protéger. [Targum Jonathan sur Deutéronome,32,10] ([Targum Jonathan sur Deutéronome,2] אקיף). [Targum Jonathan sur II Rois,20,6]. [Targum Jonathan sur Isaïe,27,3] [Jastrow, מַגִּין,1] (ed. Lag. מגן, v. [Jastrow, גְּנַן,1]) ; a. e.<br> Ithpe. - אִתְּגֵין à protéger. [Targum Jonathan sur Sophonie, 2,3] (éd. Lag. יתגן). V. [Jastrow, גְּנַן,1]. "
	},
	{
		"word": "גין",
		"description": " גִּין II m. ([Jastrow, גִּין I,1]) protection. [Targum Jonathan sur Isaïe,28,15].-בְּגִין au nom de, à cause de ; afin que. (Targum Jonathan sur la Genèse,12,13) (O. בדיל). [Targum Jonathan sur la Genèse, 18,24] ; a. fr.-[Dans le Talm. h. a. ch.] [Yevamot,89b,7] אוכלת בְּגִינוֹ וכ׳ à cause de lui (en tant que femme) elle est autorisée à manger de la T'rumah. Y. B. Kam. X, 7ᶜ top בג׳ כן donc ; a. fr.-בגין ד׳ parce que, puisque. Y. Gitt. IX, 50ᵇ ב׳ דרב וכ׳ parce que Rab et Samuel, tous deux, ont dit. Y. Bicc. II, 64ᵈ top ב׳ דכתיב parce qu'il est ainsi écrit ; a. fr. "
	},
	{
		"word": "גינא",
		"description": " גִּינָּא , v. [Jastrow, גִּינְּתָא,1] a. [Jastrow, גַּנָּא,1] [Jastrow, גַּנָּא,1]. "
	},
	{
		"word": "גינאה",
		"description": " גִּינָּאָה m. (dénom. de [Jastrow, גִּינָּא,1]) jardinier, marchand de légumes. [Chullin,105b,13]. [Shabbat,110b].-Pl. [Jastrow, גִּינַּאי,1]. [Gittin,14a,9]. [Taanit,20b,12] פייש להו לג׳ (Mme M. יתיר לגִנָּאֵי) a été laissé aux jardiniers (n'a pas été vendu). "
	},
	{
		"word": "גינאי",
		"description": " גִּינַּאי, גִּינַּיי I f. (dénom. de [Jastrow, גַּן,1], [Jastrow, גִּינָּה,1]) un ensemble de jardins, de résidences de campagne.-Pl. גִּינָּאוֹת. [Midrash Tehillim,48,5], fin ; [Yalkut Shimoni on Nach,756,1].-[Bava Batra,75b,9] Ms. M. (ed. גינואות, v. Rabb. D. S. a. l. note) ; Yalk. Zach. 568 ; v. [Jastrow, *טֶפֶף,1]. [Ar. [Jastrow, גוניות,1], גינואות, v. ed. Koh. s. v. גוננא p. 320] -Yalkut Shimoni sur la Torah,946], v. [Jastrow, *גּוּנְתָּאִי,1].] "
	},
	{
		"word": "גינאי²",
		"description": " גִּינַּאי, גִּינַּיי II m. (dénom. de [Jastrow, גִּינָּא,1] ; cmp. [Jastrow, גִּינַּאי,1]) digue pour l'irrigation des jardins ; aussi pr. n. Ginnai. [Chullin,7a,11] ג׳ נהרא le ruisseau Ginnai ; Y. Dem. I, 22ᵃ haut. Y. Shek. VI, 50ᶜ bot. ג׳ שטף זיקין une digue débordante a emporté des bouteilles de vin. "
	},
	{
		"word": "גינברא",
		"description": " גִּינְבְּרָא m. (cmp. ζιγγίβερις a. [Jastrow, זַנְגְּבִילָא,1]) gingembre. [Gittin,86a,3] "
	},
	{
		"word": "גינברא",
		"description": " גּינְבָּרָא , v. [Jastrow, גִּנְבָּרָא,1] "
	},
	{
		"word": "גינגלון",
		"description": " גִּינְגְּלוֹן , v. [Jastrow, גִּלְגְּלִין,1] "
	},
	{
		"word": "גינדרונא",
		"description": " גּינדרונא , v. [Jastrow, גִּירְדּוֹנָא,1] "
	},
	{
		"word": "גינה",
		"description": " גִּינָּה , v. [Jastrow, גַּן,1]. [Chald. = [Jastrow, גִּינָּא,1].] "
	},
	{
		"word": "גינון",
		"description": " גִּינּוּן , v. [Jastrow, גִּנּוּן,1]. "
	},
	{
		"word": "גינוניתא",
		"description": " גִּינּוּנִיתָא , v. [Jastrow, גַּנּוּנִיתָא,1] "
	},
	{
		"word": "גינוסיא",
		"description": " גִּינוּסְיָא, גִּינוּסִים, גּינוסין , v. [Jastrow, גִּינִיסְיָא,1] "
	},
	{
		"word": "גינוסר",
		"description": " גִּינֹּוסַר , v. [Jastrow, גִּינֵּיסַר,1] "
	},
	{
		"word": "גינזק",
		"description": " גִּינְזֵק , v. [Jastrow, גִּנְזָק,1] "
	},
	{
		"word": "גיני",
		"description": " גִּינִי, גִּינְיָא , v. [Jastrow, גּוּנִי,1] a. [Jastrow, גּוּנְיָא,1] [Jastrow, גּוּנְיָא,1]. "
	},
	{
		"word": "גיניאך",
		"description": " גּיניאך, גּ׳ טַעֲוָותָא lire גִּינַּיָּא דט׳. [Targum Jonathan sur Isaïe,65,3] ; [Targum Jonathan sur Isaïe,66,17] (Buxt. a. oth. ed. [Jastrow, גִּינָּא,1]), v. [Jastrow, גִּינְּתָא,1]. "
	},
	{
		"word": "גיניי",
		"description": " גִּינַּיי , v. [Jastrow, גִּינַּאי,1] "
	},
	{
		"word": "גינין",
		"description": " גִּינִּין, *(גּונין) m. pl. (גנן) armure de protection, cuirasse( ?). [Tosefta Keilim Metsia,3,1]. [V. [Jastrow, גַּנָּא, 1]. "
	},
	{
		"word": "גיניסיא",
		"description": " גִּינִיסְיָא, גִּינִיסִין, (גִּינוּ׳, גְּנוּ׳) m. pl. (γενέσια, τὰ) 1) (avec [Jastrow, יוֹם,1]) fête du bithday, anniversaire de la mort ; au gén. fête commémorative. [Targum araméen sur Esther,3,8]. [Targum Jonathan sur la Genèse,40,20] [Jastrow, גְּנוּסָא,1] (v. [Jastrow, גְּנִיסָא,1] a. [Jastrow, גְּנוּסַיָּיא,1]).- [Mishnah Avodah Zarah,1,3] ([Avodah Zarah,8a,5]) יום ג׳ של מלכים anniversaires royaux, expl. Y. ib. 39ᶜ fête d'anniversaire (avec réf. à [Genèse,40,20], v. supra) ; Bab. ib. 10ᵃ (après discussion) יום שמעמידין בו המלך installation d'un roi (empereur romain). Y. R. Hash. III, 59ᵃ haut ; Yalk. Hab. 564. [Shemot Rabba,15] יום ג׳ un anniversaire (commémoratif de son accouchement) ; a. e. -2) (= γενέθλια) descendance, noblesse de naissance. Pesik. Naḥămu p. 126ᵃ ; 126ᵇ ; [Yalkut Shimoni sur la Torah,162,3] הודעתם ג׳ שלי ([Bereishit Rabbah,100,9] הודעתי הוגנוסים corr. acc.) vous avez fait connaître ma noble descendance. Pesik. Haḥod. p. 53ᵃ בת גִּינוּסִים ; [Pesikta Rabbati,15,1] בת גינסין (lire [Jastrow, גִּינִיסְיָא,1], [Yalkut Shimoni sur la Torah,190] seulement בת טובים) une femme de noble naissance. [Shir HaShirim Rabbah,1,2] ; a. fr. Sotah,36b,19] גְּנִיסֵי מלכות וכ׳ Ar. (ed. גְּנוּנֵי) Je reconnais en lui la noblesse royale]. "
	},
	{
		"word": "גיניסר",
		"description": " גִּינֵּיסַר, (גִּינּוֹ׳, גְּנֵי׳, גְּנוֹ׳) pr. n. pl.  (Γεννησάρ, Γεννησαρέτ, une hellénisation de [Jastrow, כִּנֶּרֶת,1]) Gennesar, Gennesaret, lac, ville et district de G. [Pesachim,8b,10] פירות גינו׳ Gennes. fruits. [Bereishit Rabbah,98] (étymologie) [Jastrow, גְּנוֹסַר,1] = גני שרים jardins princiers ; [Megillah,6a,1], v. [Jastrow, כִּנָּרָא,1] ; a. e.-Pl. גִּינֵּיסַרְיוֹת. Y. Meg. I, 70ᵃ bot. שני גו׳ היו (corr. acc.) y avait-il deux lieux du nom de G. ? "
	},
	{
		"word": "גינירות",
		"description": " גינירות , [Tosefta Menahot,9,3], Var. ניטרות, lire נינורות , v. [Jastrow, נִיר,1] "
	},
	{
		"word": "גינניא",
		"description": " גִּינָּנַיָּא , v. [Jastrow, גַּנָּא,1] "
	},
	{
		"word": "גינסין",
		"description": " גינסין , v. [Jastrow, גִּינִיסְיָא,1] "
	},
	{
		"word": "גינתא",
		"description": " גִּינְּתָא, גִּינָּא, גִּנּ׳ f. (גנן, v. [Jastrow, גַּן,1]) jardin. [Onkelos Genèse,2,8]. Targ. Y. I Gen. XLXI, 4 גינא (Y. II [Jastrow, גַּנָּא,1]). [Targum araméen aux Psaumes,56,14] (deuxième verset). Constr. [Jastrow, גִּינָּא,1]. [Onkelos Deuteronomy,11,10] ; a. fr.-[Bereishit Rabbah,80,12] (prov.) לפום ג׳ גננא comme le jardin donc le jardinier (comme le peuple donc le chef) ; Y. Snh. II, 20ᵈ top כגִנְּתָה כן גננה. [Bava Batra,54a] ; a. fr.-Pl. [Jastrow, גִּינְּתָא,1], constr. [Jastrow, גִּינָּא,1]. [Targum araméen sur Ecclésiaste,2,5].- [Jastrow, גִּינָּא,1], [Jastrow, גַּנָּן,1]. [Targum Jonathan sur Isaïe, 65,3] ; [Targum Jonathan sur Isaïe, 66,17] (certaines éditions [Jastrow, גַּנָּן,1] ; v. [Jastrow, גּיניאך,1]). V. [Jastrow, גַּנָּא,1]. "
	},
	{
		"word": "גיס",
		"description": " גֵּיס m. (גנס ; cmp. גנז a. כנס ; Syr. גסא divitiae P. Sm. 757) butins, trésors entassés.  Pl. גִּיסִּין. [Shemot Rabba,9,7] (réf. à [Esther,1,4]) ששה ג׳ וכ׳ il leur montrait chaque jour six collections, et pas deux pareilles ; Esth. R. à l. c. ששה ג׳ היה פותח וכ׳ (ed. ניסין, נוסין, corr. acc.) six trésors qu'il leur ouvrit &c. ; ([Yalkut Shimoni on Nach,1046,5] תסבוריות ; Targ. II Esth. I, 4 בי גנזי). "
	},
	{
		"word": "גיס",
		"description": " גִּיס II, גָּיֵיס m. (גּוּס II) intime, familier. [Ketubot,85b,7] ואי ... דגִ׳ ביה הא גִ׳ ביה (Ar. ... דגייס ... גָס ביה) mais si c'est quelqu'un qui lui est familier (au point d'utiliser son nom sans titre), alors, on peut dire qu'il a parlé de lui de façon familière.-Fem. [Jastrow, גָּיְיסָא,1]. [Kiddushin,81a,13] ג׳ ביה elle était en bons termes avec lui.-Pl. גִּיסֵי, גָיְיסֵי. [Kiddushin,33a,16] דגִי׳ בה רבנן où les savants sont un spectacle familier (et où on ne leur prête pas attention). [Ketubot,28a,5] גיי׳ בהדדי ils sont intimes les uns avec les autres. "
	},
	{
		"word": "גיס²",
		"description": " גִּיס II m. (v. [Jastrow, גִּיס II,1], cmp. [Jastrow, גִּיסָא III,1]) le mari de la sœur de la femme, le beau-frère. [Mishna Sanhedrin,3,4] ([Sanhedrin,27b]) גִּיסוֹ (Y. ib. III, 7 אֲגִיסוֹ) ; a. fr.-Pl. גִּיסִין. Y. Shek. I, fin, 46ᵇ ; a. e. "
	},
	{
		"word": "גיסא",
		"description": " גִּיסָא I, אֲגִיסָא ch. [Jastrow, גִּיס II ²,1].  Y. Snh. III, 21ᵇ bot. אֲגִיסֵיה דר׳ וכ׳ beau-frère de R. H..-Pl. גִּיסֵי. [Sanhedrin,28b,21] אחי וג׳ frères et beaux-frères (deux frères ayant épousé deux sœurs). [Sanhedrin,28b,19] תרי ג׳. "
	},
	{
		"word": "גיסא",
		"description": " גִּיסָא II, גָּיְיסָא m. (גוס I) homme audacieux. [Chullin,18b,10] il cria sur lui ג׳ ג׳ (Ar. ed. Koh. גיי׳ וגיי׳) homme audacieux que tu es ! "
	},
	{
		"word": "גיסא",
		"description": " גִּיסָא III m. (גוס II) quartier, côté. [Kiddushin,33a,14] באידך ג׳ de l'autre côté (de la rivière) ; [Eruvin,16b,17]. [Shabbat,110a,1] בההוא ג׳ וכ׳ dans un certain quartier de &c.-[Yoma,77b,11]. [Bekhorot,44b] [Jastrow, אִיגַּרְתָּא,1] de côté. [Kohelet Rabbah,7,9] quand la bouilloire déborde, על גיסיה שפיך elle se déverse sur ses propres parois (la colère ne blessera personne d'autre que l'homme lui-même) ; a. fr.-Trnsf. manière, façon. [Gittin,67b,4] certains soutiennent להאי ג׳ וכ׳ une façon et d'autres l'autre ; a. fr.-[Niddah,66a,39] [lire :] לא תגלי ... דכי היכי דתהוו עליך להן ג׳ וכ׳ (v. Ar. ed. Koh. s. v. דם IV, 752) ne le dis pas à tes amis, car comme ils se sont étonnés de toi d'un côté (de ta malchance), ils pourraient s'étonner de l'autre côté (de ta bonne fortune, et l'ensorceler). Chullin,17b] אתרי גִיסָנֵי, Sh'eltoth d'R. Aḥai 92, éd. אתלת רוחתא]. "
	},
	{
		"word": "גיסה",
		"description": " גִּיסָה, גִּיזָה f. (v. [Jastrow, גֹּוסֵס,1]) agonie de la mort, stade de la mort. Y. Sot. IX, 23ᵈ bot. מקום גִּיסָתָהּ le lieu où mourait la génisse expiatoire ; [Tosefta Sotah,9,1] גִּיזָתָהּ. "
	},
	{
		"word": "גיסטרא",
		"description": " גִּיסְטְרָא, גִּסְטְרָא, גִּצְטְרָא f. (= גזרזרא, un reduplic. de גזר ; pour l'assimilation des sibilants cmp. Nöld. Mand. Gr. p. 45 sq.) quelque chose de défectueux, de mutilé ; 1) un grand récipient qui s'est avéré défectueux ou peu maniable, parce que ses anses ont été cassées ou qu'il est fendu, et qui est donc utilisé comme réceptacle pour les déchets, comme marmite, comme récepteur des égouttures d'un récipient qui fuit, etc. [Mishnah Kelim,2,6] גס׳ שנמצאת וכ׳ (Ar. un récipient défectueux trouvé dans le four (dans lequel on met les récipients pour la cuisson) ; Tosef. ib. [Mishna Bava Kamma,3,10] ואם היתה גסטרה mais si la cruche est devenue une gistra, contredit נפחתה. Ib. אי זו היא גסטרא כל שנסדקין אזניה וכ׳ ([Mishnah Kelim,4,3] גיס׳ כל שניטלו וכ׳ ...) quand un récipient est-il appelé gistra ? Lorsque ses anses sont fendues (cassées) &c. Ib. 2 גי׳ שנתרועעה וכ׳ si une gistra est brisée au point de ne plus être un réceptacle pour les liquides, bien qu'elle puisse encore recevoir des comestibles, elle n'est pas susceptible d'impureté, car il n'y a pas de fragment de fragment, c'est-à-dire un fragment de gistra. Le fragment d'une gistra n'est plus considéré comme un récipient. [Chabbat,96a,1] (une gistra qui fuit n'est pas considérée comme un récipient) car personne ne dit הָבֵא ג׳ לג׳ apporter une g. à mettre sous une gistra ; a. fr. -2) un corps d'animal mutilé jusqu'à la défiguration. [Chullin,21a,9] ; [Chullin,32b,7] עשאה ג׳ נבלה si l'on a fait d'un animal une gistra en lacérant certains de ses membres, il est considéré comme une carcasse. [Chullin,52a,19] ג׳ קאמריתו vous parlez d'un corps mutilé (une côte de chaque côté disjointe) ! [Chullin,27a,7] דלא לישוייה ג׳ qu'en égorgeant l'animal on ne doit pas en faire une gistra (en coupant la tête). [Sanhedrin,52b,15] דעביד ליה ג׳ que le coupable soit coupé en deux.- [Chullin,124a,11] דעבדיה ג׳ il fendit le poêle dans le sens de la longueur.-Pl. גִּיסְטְרָאוֹת, [Jastrow, גַּסְטְרָיוֹת,1]. [Tosefta Kelim Kamma,3,8] שרובן מן הג׳ car la plupart des fragments de poterie trouvés chez le potier proviennent de récipients mal formés. [Mishna Makhshirin,2,3] ג׳ שישראל וכ׳ pots dans lesquels les Israélites et les gentils jetaient leurs déchets.-Y. Sabb. III, beg. 5ᶜ ממלא גִּצְרָא וכ׳ on peut remplir un grand pot de cendres chaudes &c. -3) (castra) camp, v. [Jastrow, גַּסְטְרָא,1]. "
	},
	{
		"word": "גיסטרון",
		"description": " גיסטרון , v. [Jastrow, גַּסִּיטְרוֹן,1]. "
	},
	{
		"word": "גיססא",
		"description": " גִּיסְסָא I m. (גוס II, v. [Jastrow, גִּיסָא III,1] a. [Jastrow, גֶּסֶס,1]) 1) côté, bras.-Pl. גִּיסְסִין. [Targum Jonathan sur Isaïe,60,4] ; [Targum Jonathan sur Isaïe,66,13] (texte h. [Jastrow, צַד,1]). -2) Pl. גִּיסְסַיָּא, גִּסְ׳ loins. [Onkelos Leviticus,3,4] ; [Onkelos Leviticus,3,15] (h. texte כסלים, Y. כפליא). "
	},
	{
		"word": "גיססא",
		"description": " גִּיסְסָא II m. (cmp. [Jastrow, גָּשׁוֹשׁ,1]) long pôle.-Pl. גִּיסְסִין, גִּסְ׳. (Targum Jonathan sur II Samuel, 18, 14) (Ar. [Jastrow, גסיסין, 1], h. texte שבטים). "
	},
	{
		"word": "גיסתרא",
		"description": " גיסתרא , v. [Jastrow, גַּסְטְרָא,1] "
	},
	{
		"word": "גיעגוע",
		"description": " גִּיעֲגוּעַ , v. גִּעֲ׳ "
	},
	{
		"word": "גיעול",
		"description": " גִּיעוּל I m. ([Jastrow, גָּעַל,1]) le nettoyage d'un récipient impur au moyen d'eau bouillante ([Nombres,31,23]), v. [Jastrow, הַגְעָלָה,1]. [Zevachim,97a,5] ; [Avodah Zarah,76a,5] כל יום ... ג׳ לחבירו chaque jour l'ébullition faite dans le vase sacré est le moyen d'absorber les imprégnations de la veille.-Pl. גִּיעוּלִים, constr. גִּיעוּלֵי ; (גוים, עכו \"ם) ג׳ גכרים récipients des gentils qui nécessitent un nettoyage à l'eau bouillante avant de pouvoir être utilisés par les juifs. Ib. 67ᵇ ; 75ᵇ ; a. fr. "
	},
	{
		"word": "גיעול",
		"description": " גִּיעוּל II m. ([Jastrow, גָּעַל,1], v. [Job,21,10]), pl. constr. גִּיעוּלֵי, ג׳ בצים œufs avortés chassés en frappant la poule. [Tosefta Terumot,9,5] ; Y. ib. X, 47ᵇ bot. ; [Chullin,64b,2] (Rachi : œufs échaudés dans l'eau chaude en même temps que les œufs interdits, v. [Jastrow, גִּיעוּל I,1]). "
	},
	{
		"word": "גיף",
		"description": " גֵּיף m. (b. h. [Jastrow, גַּף I,1] [Jastrow, גַּף I,1]) côté, rive. [Mishna Makhshirin,1,4] על ג׳ הנהר Ar. (ed. [Jastrow, גַּב,1], R. Hai Gaon [Jastrow, גַּף I,1], v. Koh. Ar. Compl. s. v. note 9). "
	},
	{
		"word": "גיף²",
		"description": " גֵּיף, גֵּיפָא ch. [Jastrow, גֵּיף,1].  [Targum Jonathan sur l'Exode, 14,9]. [Targum Jonathan sur l'Exode, 15,9] (Y. II certains ed. [Jastrow, גַּף I,1]). Ib. II, 5 (Y. II [Jastrow, גַּב,1], O. [Jastrow, כֵּיף,1]) ; a. e.-Y. Kidd. I, 58ᵈ ; Y. Keth. VI, fin 31ᵃ אייתיבוני על ג׳ נהרא וכ׳ placez-moi au bord d'un fleuve, et si je ne ..., jetez-moi dans le fleuve. Ib. XIII, 35ᵇ bot. ([Jastrow, גּוּף,1], corr. acc.) ; Y. Kil. IX, 32ᶜ bot. ; a. fr. "
	},
	{
		"word": "*גיף",
		"description": " *גִּיף m. (גּוּף I) adultère, sensualité. [Shabbat,104a,12], v. [Jastrow, אח]. "
	},
	{
		"word": "גיפא",
		"description": " גַּיָּפָא , v. [Jastrow, גַּיָּיפָא,1]. "
	},
	{
		"word": "גיפוף",
		"description": " גִּיפּוּף m. (גפף) 1) embrasser, étreindre. [Sanhedrin,56b,13] ג׳ ונישוק étreindre et embrasser les idoles. -2) la fermeture. Y. Sabb. III, 5ᵈ bot. אחר גִּיפּוּפוֹ selon que le poêle est refermé. "
	},
	{
		"word": "גיפוף²",
		"description": " גִּיפּוּף, גֵּיפּוּפָא, גִּפּ׳, גֵּפ׳ ch. (cmp. [Jastrow, גִּיפּוּף,1]) rampe, rebord. [Targum Jonathan sur Exode,25,25] ; [Targum Jonathan sur Exode,25,27] (texte h. [Jastrow, מִסְגֶּרֶת,1] ; O. [Jastrow, גְּדָנְפָא,1]).-Pl. גִּיפוּפִין, גִּיפוּפֵי. [Targum Jonathan sur Deutéronome,22,8] ([Targum Jonathan sur Deutéronome,2] גופוף). [Eruvin,89b,8] "
	},
	{
		"word": "גיפטי",
		"description": " גִּיפְטִי m. (Αἰγύπτιος) épyptien, copte.-Pl. [Jastrow, גִּיפְטִי,1]. [Megillah,18a,19] גיפטית לג׳ (Ar. גפתית לגפתים) aux Juifs égyptiens &c.-Fem. [Jastrow, גִּיפְטִי,1] en langue égyptienne ou copte. Ib.- [Shabbat,115a,6]. [Shabbat,115b] תנא דג׳ l'auteur de la règle concernant les écrits sacrés en égyptien &c. ([Shabbat,115a,6]). Cmp. [Jastrow, *גִּיוָוטָאֵי,1]. "
	},
	{
		"word": "גיפן",
		"description": " גיפן , v. [Jastrow, *גּוֹפֶן,1] "
	},
	{
		"word": "גיפסוס",
		"description": " גִּיפְסוֹס m. (γύψος) gypse. Y. Sabb. II, 5ᵃ top ; v. [Jastrow, גִּפְסִים,1]. "
	},
	{
		"word": "גיפסים",
		"description": " גִּיפְסִים, גיפסיס , v. [Jastrow, גִּפְסִים,1]. "
	},
	{
		"word": "גיפף",
		"description": " גִּיפֵּף , v. [Jastrow, גָּפַף,1] "
	},
	{
		"word": "גיפר",
		"description": " גִּיפֵּר , v. [Jastrow, גָּפַר,1] "
	},
	{
		"word": "גיפתא",
		"description": " גִּיפְתָּא, (גּוּפְ׳) ch. = h. [Jastrow, גֶּפֶת,1] une sorte de tourbe ou de gazon. Y. Sabb. IV, 6ᵈ [lire :] כמראי גו ג׳ Je l'ai gardé au chaud dans la gifta. [Yoma,2a] על ג׳ sur le dessus de la gifta. "
	},
	{
		"word": "גיפתי",
		"description": " גיפתי , [Eruvin,64a] (manque dans Ms. M.), version marginale [Jastrow, דִּיפְתִּי,1] q. v. "
	},
	{
		"word": "גיפתן",
		"description": " גֵּיפְתָן, גֵּיפְתָנָא, גֵּיפְתָנוּתָא , v. [Jastrow, גֵּיוְתָא,1] "
	},
	{
		"word": "גיצא",
		"description": " גֵּיצָא m. ch. = h. [Jastrow, גֵּץ,1] spark. [Targum araméen de Job, 18,5] Ms. Var. pour [Jastrow, גִּיהַּ,1].-Pl. גֵּיצִין, גִּיצִין. [Targum araméen de Job,5,7] (Ms. גֵּי׳ (ed. גִּי׳, ed. Vien. נצין). [Targum araméen à Job,41,11] Ms. (éd. [Jastrow, גּוּצִין,1]). [Targum araméen des Psaumes,140,11] (ed. Vien. ניצין). "
	},
	{
		"word": "*גיר",
		"description": " *גִּיר I (syriaque [Jastrow, גִּיר,1], P. Sm. 709 sq., prob. fr. [Jastrow, גָּרַר I,1], cmp. [Jastrow, גְּרָרָא I,1]) comme conséquence, pour &c. [Targum araméen des Proverbes,29,19] (en accord avec le Peshito) ידע ג׳ דלא בליע ed. Lag. (Var. [Jastrow, וָלָא,1], éd. דידע ג׳ ולא וכ׳, Peshito ... בלע) car il comprend (en se faisant parler) seulement qu'il ne recevra aucun coup. Targum araméen aux Proverbes,23,14] אנת ביר וכ׳ Ms. (manque dans l'éd.), lire : [Jastrow, גִּיר,1] (comme dans Peshito) tu, donc, &c.] "
	},
	{
		"word": "גיר",
		"description": " גִּיר II m. (b. h. [Jastrow, גֵּר,1] ; [Jastrow, גָּרַר I,1] ou [Jastrow, גּוּר,1] bouillir, effervescence, v. H., v. H. Dict. s. v.) 1) chaux. [Shabbat,80b] ביצת הג׳ Ar. (éd. הסיד), v. [Jastrow, בֵּיצָה,1].-Dénom. [Jastrow, גִּיֵּיר,1], plâtrer. [Eichah Rabbah,2,8] Ar. (ed. סייד).- [Chullin,88b] bot. הג׳ והזרניך quot. dans Rashi à [Exode,16,14] (éd. seulement הז׳) chaux en poudre et orpiment. -2) pierre à encre, ou sulfate de fer (sory). [Beitzah,15a,6] ביצת הג׳ un morceau de pierre à encre (pour noircir le cuir).-Au gén. poudre, au composé [Jastrow, גִּירְגִּבְסִין,1] poudre de gypse ; גִּירְקְרָרִין poussière de cire, v. [Jastrow, *אַגֵּין,1]. Y. Sabb. VII, 10ᵇ bot. (perh. à lire en deux mots : chaux, gypse &c.). -3) écume. [Mishna Menachot,8,7] ([Menachot,87a,2]) זרק הג׳ (Mish. ז׳ את הגיד, corr. acc.) si l'écume (du vin en fermentation) éclate ; Tosef. ib. IX, 11 ג׳ של שמרים. "
	},
	{
		"word": "גיר",
		"description": " גִּיר, גִּירָא I ch. [Jastrow, גִּיר II,1] , chaux, plâtre. [Daniel,5,5].- [Onkelos Exode,16,14] דעדק כג׳ mince et cassant comme une couche de chaux (h. texte מחספס). [Targum Jonathan sur Deutéronome,27,2] (texte h. [Jastrow, סִיד I,1]) ; a. e.-2) écume, mousse.  Pl. גִּירִין [Targum Jonathan sur Exode,15,10] ג׳ דימא les flots écumants. Le Targum Jonathan sur Jérémie,9,14], lit כגידין, v. [Jastrow, גִּידָּא II,1].]-3) nom d'une maladie, une sorte de fièvre ( ?). [Gittin,69b,2], v. [Jastrow, גִּיר III,1]. "
	},
	{
		"word": "גיר",
		"description": " גִּיר III, גִּירָא II, גִּירְרָא m. ([Jastrow, גרי,1], [Jastrow, גָּרַר I,1] ; cmp. b. h. [Jastrow, שֶׁלַח,1]) 1) projectile, flèche. [Targum Jonathan sur Isaïe, 37,33]. [Targum araméen sur Job,41,20] ; a. fr.-[Gittin,56a,6] שדא ג׳ וכ׳ il a tiré une flèche vers l'est. [Bava Kamma,26b,10] בעידנא דשדייה פסוקי מפסקי גִירֵיה (v. Rabb. D. S. a. l. note) au moment où il a décoché sa flèche, sa force était brisée, c'est-à-dire qu'au moment où il a jeté le récipient, des polsters étaient là pour empêcher sa rupture. [Sukkah,38a,1] דין ג׳ בעיניה וכ׳ c'est une flèche dans les yeux du tentateur, c'est-à-dire que cela nous permet de le défier. [Il faut dire à Satan : ג׳ בעיניך je te défie ; [Kiddushin,81a,15]. -[Taanit,25a,14] אגרי בך גִירַי Je lâcherai ma flèche contre toi (v. Rabb. D. S. a. l. note ; autres vers. v. [Jastrow, גּוּר,1] I ch.). [Pessahim, 28a,5], v. [Jastrow, גִּירָאָה,1] ; a. fr.-ג׳ דלילתא (Ar. דלוליתא) la flèche de Lilith, supposée être une pierre météorique en forme de coin. [Gittin,69b,2] לגירא ליתי ג׳ דל׳ comme remède à la gira (v. [Jastrow, גִּיר,1]) qu'on obtienne une gira de &c.-Pl. גִּירִין, [Jastrow, גֵּירִי,1], גִּירַיָּא ; גִּירְרִין, גִּירְרַיָּא. [Targum Jonathan sur II Samuel,1,22]. [Targum Jonathan sur Genèse,49,23], [Targum Jérusalem, Genèse,49,23] (pas גיד׳). [Targum araméen des Psaumes, 120,4] ; a. fr.-[Sanhedrin,108b,21] גילי והוו ג׳ il a jeté l'ivraie et elle s'est transformée en flèches. [Bava Batra,73a] ; v. בְּזַק. Y. ib. II, 13ᵇ bot. מן קל גורי וכ׳ (acc. corr.) du sifflement des flèches ; a. fr. -2) pousse d'une plante. Pl. [Jastrow, גֵּירִי,1]. [Shabbat,109b] ג׳ דרוביא pousses de fenugrec ; (oth. opin. in Ar. graines de lin, Ms. O. [Jastrow, גִּידָּא I,1], v. [Jastrow, גִּידָּא I,1]). "
	},
	{
		"word": "גירא",
		"description": " גִּירָא III m. ([Jastrow, גָּרַר I,1] ; cmp. [Jastrow, גְּרָרָא I,1]) conséquence directe d'un acte. . [Bava Batra,22b,12] בגירי דידיה (Rashi דיליה) ; [Bava Batra,25b] sq. בגִירֵיה דיליה (Ms. M. seulement בגיריה, v. Rabb. D. S. a. l. note) ; [Bava Metzia,117a,12] בגירי דיליה lorsque le dommage est le résultat direct de son acte. [Bava Metzia,44a,3] גירי דידיה וכ׳ c'est son acte qui l'a aidé (à s'aigrir). [Rachi : ses flèches dans un sens métaphorique, v. précédent]. "
	},
	{
		"word": "גירא",
		"description": " גִּירָא IV pr. n. f., v. [Jastrow, גִּילָא I,1] "
	},
	{
		"word": "גירא",
		"description": " גֵּירָא ch. = h. [Jastrow, גֵּר,1] [Jastrow, גֵּר,1].  . [Taanit,25a,14], v. [Jastrow, גּוּר,1] I ch. "
	},
	{
		"word": "גיראה",
		"description": " גִּירָאָה m. (dénom. de [Jastrow, גִּיר III,1]) tireur, (Rachi :) fabricant de flèches. [Pesachim,28a,5] (prov.) ג׳ בגִירֵיה מקטיל וכ׳ (éd. [Jastrow, גֵּירָא,1], corr. acc, v. Rabb. D. S. a. l. note) lorsque le tireur (fabricant de flèches) est tué par sa propre flèche, il est payé avec les spins de sa propre main. "
	},
	{
		"word": "גירגבסין",
		"description": " גִּירְגִּבְסִין , v. [Jastrow, גִּיר II,1], 2). "
	},
	{
		"word": "גירגר",
		"description": " גִּירְגֵּר , v. [Jastrow, גָּרַר I,1]. "
	},
	{
		"word": "גירדא",
		"description": " גִּירְדָּא I m. ([Jastrow, גְּרַד,1]) grattage, croûte. [Shabbat,109b] גי׳ דאסניתא (ed. גו׳ דאסינתא) l'épluchage de &c., v. [Jastrow, אַסְנִיתָא,1]. [Ketubot,77b,4], v. [Jastrow, *אַשְׁפָּא,1]. [Avodah Zarah,28a,13] גְּרָדָא דיבלא וגי׳ דאסנא (Mme M. גררא ... וגוררא, première édition וגורדא) racine grattée de cynodon et le parage de la ronce. [Sotah,10b] ; [Bamidbar Rabbah,9,24] (prov.) קמי דשתי חמרא חמרא קמי רפוקא גי׳ דיבלא devant les buveurs de vin, placer le vin ; devant un laboureur, un plat de racines raclées &c. V. [Jastrow, גַּרְדָּא,1]. "
	},
	{
		"word": "גירדא",
		"description": " גִּירְדָּא II m. ([Jastrow, גָּדַד I,1], avec [Jastrow, ר,1] inséré) souche, tige. [Pesachim,111b] top גי׳ דדיקלא (Var. [Jastrow, גִּידָּא I,1], [Jastrow, גּוּדָּא I,1], v. Rabb. D. S. a. l. note 30) la tige d'un palmier (Ar. : écorce, v. [Jastrow, גִּירְדָּא I,1]). [Bava Metzia, 86a] (Mme M. גידרא, Mme R. 2 גיררא, v. Rabb. D. S. a. l. note). "
	},
	{
		"word": "גירדא",
		"description": " גִּירְדָּא, גִירְדַּאי , v. גַּרְדּ׳ "
	},
	{
		"word": "גירדונא",
		"description": " גִּירְדּוֹנָא, (גִּידְרוֹנָא) m. (cmp. [Jastrow, *גַּיְידּוֹר,1]) un jeune âne. [Nedarim,41a,8] "
	},
	{
		"word": "גירדי",
		"description": " גִּירְדַּי, גִּירְדָּנָא , v. גַּרְדּ׳ "
	},
	{
		"word": "גירה",
		"description": " גֵּירָה , v. [Jastrow, גרי,1] "
	},
	{
		"word": "גירה",
		"description": " גִּירָה , Pi. de [Jastrow, גרי,1]. "
	},
	{
		"word": "גירוי",
		"description": " גֵּירוּי m. ([Jastrow, גרי,1]) instigation, provocation, excitation. [Sifrei Devarim,87,2], v. [Jastrow, הַסָּתָה,1] ; [Yalkut Shimoni sur la Torah,886,3]. Tanḥ. Balak. 2 (réf. à [Deutéronome,2,19]) כל מיני ג׳ toute sorte de provocation (est interdite) ; [Bamidbar Rabbah,20], beg. [Jastrow, גירור,1] (acc. corr.) ; [Yalkut Shimoni sur la Torah,765,10]. "
	},
	{
		"word": "גירומים",
		"description": " גֵּירוּמִים, גֵּירוּמִין m. pl. ([Jastrow, גְּרַם I,1]) ce qui va avec, ajout habituel au poids ou à la mesure lors des ventes. [Mishna Bava Batra,6,11] נותן לו גֵּירוּמָיו (Bab. ed. 88ᵇ מין ..., Y. ed. ... [Jastrow, מַיִם,1]) il doit lui donner le surplus dû. Sifra K'doshim Par. 9, ch. VIII. "
	},
	{
		"word": "גירומסין",
		"description": " גירומסין , v. [Jastrow, *גרמסין,1]. "
	},
	{
		"word": "גירונין",
		"description": " גירונין , [Targum de II Chroniques,20,25], certaines éditions lisent ריגונין. "
	},
	{
		"word": "גירוע",
		"description": " גֵּירוּעַ I m. ([Jastrow, גָּרַע I,1]) I) déduction du prix du rachat selon les années de possession ([Lévitique,27,18]). [Arakhin,24a,32] ליגאל בג׳ à racheter avec la déduction due. [Bava Metzia,106a] l'année du sabbat לא תעלה לו בג׳ Ar. (ed. מן הג׳, v. Rabb. D. S. s. l. note 90) ne doit pas être comptée dans la déduction.-Pl. [Jastrow, גֵּרוּעַ,1]. Y. Shebu. VI, beg. 36ᵈ סוף גֵּירוּעֶיהָ la rédemption finale de la servante hébraïque. "
	},
	{
		"word": "גירוע",
		"description": " גֵּירוּעַ II, גֵּרוּעַ m. (גָּרַע II) la formation de globules ou de grains dans le raisin. [Berakhot,36b,10] ; [Pesachim,53a,1] הוא בוסר הוא ג׳, v. [Jastrow, בֹּוסֶר,1]. "
	},
	{
		"word": "גירור",
		"description": " גירור , v. [Jastrow, גֵּירוּי,1]. "
	},
	{
		"word": "גירושין",
		"description": " גֵּירוּשִׁין , v. [Jastrow, גֵּרוּשִׁין,1] "
	},
	{
		"word": "גירות",
		"description": " גֵּירוּת , v. [Jastrow, גֵּרוּת,1] "
	},
	{
		"word": "גירותא",
		"description": " גִּירוּתָא f. girutha, nom d'un oiseau impur, supposé être la poule mouillée. [Chullin,62b,7] ; [Niddah,50b,24] expl. la poule des marais. [Chullin,109b,13] il nous est interdit [Jastrow, ג׳,1] de manger de la girutha. [Ar. [Jastrow, גּוּרְיְתָא,1], v. Koh. Ar. Compl. II, 378ᵃ]. "
	},
	{
		"word": "גירי",
		"description": " גֵּירִי m. (dénom. de [Jastrow, גֵּר,1]) appartenant à une famille de convertis, descendant de prosélytes. [Mishnah Kiddushin,4,1] (collectivement) ; v. Tos'foth Yom Tob a. l. s. v. [Jastrow, כֹּהֲנִי,1]. "
	},
	{
		"word": "גירמא",
		"description": " גִּירְמָא , v. [Jastrow, גַּרְמָא,1]. "
	},
	{
		"word": "גירמניא",
		"description": " גִּירְמַנְיָא, גִּירְמַנִיקִי , v. גִּרְמַ׳ "
	},
	{
		"word": "גירסא",
		"description": " גִּירְסָא I, גִּרְסָא m. (גְּרַס II) apprentissage acquis, tradition, étude par cœur. [Targum araméen du Cantique des Cantiques,1,2] בג׳ pour l'étude par cœur (tradition orale).-[Megillah,6b,4] לאוקומי ג׳ וכ׳ pour préserver (se souvenir) de ce que l'on a appris, nécessite une assistance divine. [Chabbat,21b,2] ג׳ דינקותא acquis dans la prime jeunesse (dont on se souvient mieux). [Shabbat,30b,1] לא ... פומיה מג׳ n'ont pas cessé d'étudier par cœur ; [Bava Metzia,86a,8] מגִּרְסֵיה.-Pl. גִּירְסַיָּיא. [Bava Batra,22a] ils peuvent être perturbés. מגִּירְסַייְהוּ dans leurs études. [Dans la littérature ultérieure [Jastrow, גִּירְסָא I,1] version]. "
	},
	{
		"word": "גירסא",
		"description": " גִּירְסָא II v. [Jastrow, גִּירְצָא,1] "
	},
	{
		"word": "גירסנא",
		"description": " גִּירְסָנָא, (גּוּרְסִינָא) m. (גְּרַס II ; b. h. [Ezekiel,45,9]) acquisition, épargne. [Yevamot,117a,11]. [Yevamot,117a,11] [Jastrow, גִּירְסָנָא,1] (Rachi גִּירְסְנָאִי) ce qui est accumulé pour moi. "
	},
	{
		"word": "גירעון",
		"description": " גֵּירָעוֹן, גֵּרָ׳ m. (= [Jastrow, גֵּירוּעַ I,1]) déduction. [Arakhin,25b,30] בת ג׳ soumis à la loi de la déduction. [Mishna Arakhin,9,7] ([Arakhin,33a,29]) ובג׳ כסף ... יוצאים reviennent à leurs propriétaires l'année du Jubilé ou avec une déduction du prix d'achat ([Lévitique,25,27]). [Mishnah Kiddushin,1,2] (de l'esclave hébreu) ; a. e. "
	},
	{
		"word": "גירצא",
		"description": " גִּירְצָא m. (גרץ, v. [Jastrow, גְּרִיצָה,1]) mettre des couches de pâte les unes sur les autres. [Pessahim, 37a] נפישא בג׳ Ar. (ed. Koh. בלישא בגירסא, ed. בלִישָׁה) parce qu'elle s'épaissit par combinaison. "
	},
	{
		"word": "גירקררין",
		"description": " גִּירְקְרָרִין , v. [Jastrow, גִּיר II,1], 2). "
	},
	{
		"word": "גיררא",
		"description": " גִּירְרָא flèche, v. [Jastrow, גִּיר III,1]. "
	},
	{
		"word": "גיררתו",
		"description": " גיררתו , [Kohelet Rabba,4,14,1] מבית ג׳ של פרעה, lire : גְּדֵירָתוֹ (v. [Jastrow, גְּדֵירָה,1]) de la forteresse de Pharaon (où il était en prison). "
	},
	{
		"word": "*גיש",
		"description": " *גִּישׁ m. (v. [Jastrow, גִּיס II,1]) familier. [Yevamot,117b,3] דג׳ לה וכ׳ Ar. (ed. דרגיש) l'ennui des querelles familiales lui est familier. "
	},
	{
		"word": "גישה",
		"description": " גִּישָׁה f. (נגש) s'approcher de l'autel ([Exode,30,20]). [Yoma,32b,10]. [Zevachim,19b,22] ; a. fr. "
	},
	{
		"word": "גישרא",
		"description": " גִּישְׁרָא , v. [Jastrow, גִּשְׁרָא,1]. "
	},
	{
		"word": "גישתא",
		"description": " גִּישְׁתָּא , v. [Jastrow, גִּשְׁתָּא,1] "
	},
	{
		"word": "גישתמא",
		"description": " גִּישְׁתְּמָא m. (réduplic. de [Jastrow, גָּשַׁם,1]) seuil de porte, arrêt de porte ; v. [Jastrow, גְּשָׁמָה,1]. "
	}
]